contextily/__init__.py
contextily/place.py
contextily/plotting.py
contextily/tile.py
contextily-1.5.2.dist-info/LICENSE.txt
contextily-1.5.2.dist-info/METADATA
contextily-1.5.2.dist-info/WHEEL
contextily-1.5.2.dist-info/top_level.txt
contextily-1.5.2.dist-info/RECORD
