Metadata-Version: 2.1
Name: contextily
Version: 1.5.2
Summary: Context geo-tiles in Python
Author-email: Dani Arribas-Bel <daniel.arribas.bel@gmail.com>
Maintainer: contextily contributors
License: 3-Clause BSD
Project-URL: Home, https://github.com/geopandas/contextily
Project-URL: Repository, https://github.com/geopandas/contextily
Classifier: License :: OSI Approved :: BSD License
Classifier: Programming Language :: Python :: 3
Classifier: Framework :: Matplotlib
Requires-Python: >=3.8
License-File: LICENSE.txt
Requires-Dist: geopy
Requires-Dist: matplotlib
Requires-Dist: mercantile
Requires-Dist: pillow
Requires-Dist: rasterio
Requires-Dist: requests
Requires-Dist: joblib
Requires-Dist: xyzservices
